{
  "parameters": [
    {
      "name": "Time",
      "type": "isotime",
      "length": 24
    },
    {
      "name": "MAGNETIC FIELD VALUE 1",
      "type": "double",
      "units": "",
      "description": "",
      "size": [
        1
      ]
    },
    {
      "name": "MAGNETIC FIELD VALUE 2",
      "type": "double",
      "units": "",
      "description": "",
      "size": [
        1
      ]
    },
    {
      "name": "MAGNETIC FIELD VALUE 3",
      "type": "double",
      "units": "",
      "description": "",
      "size": [
        1
      ]
    },
    {
      "name": "MAGNETIC FIELD VALUE 4",
      "type": "double",
      "units": "",
      "description": "",
      "size": [
        1
      ]
    },
    {
      "name": "MAGNETIC FIELD VALUE 5",
      "type": "double",
      "units": "",
      "description": "",
      "size": [
        1
      ]
    },
    {
      "name": "MAGNETIC FIELD VALUE 6",
      "type": "double",
      "units": "",
      "description": "",
      "size": [
        1
      ]
    }
  ],
  "description": "",
  "startDate": "",
  "stopDate": "",
  "_meta": {
    "source": "label"
  }
}
